most_queue/__init__.py
most_queue/constants.py
most_queue/structs.py
most_queue/io/__init__.py
most_queue/io/plots.py
most_queue/io/tables.py
most_queue/misc/approx_cdf_make.py
most_queue/misc/calc_v_pls.py
most_queue/misc/compare_fj_calc.py
most_queue/misc/flow_sum.py
most_queue/misc/run_mgn_with_h2_delay_cold_warm.py
most_queue/misc/vacations_paper_utils.py
most_queue/misc/tests/test_fj_delta.py
most_queue/misc/tests/test_network_opt_approx.py
most_queue/misc/tests/test_network_opt_plus.py
most_queue/random/__init__.py
most_queue/random/distributions.py
most_queue/random/distributions.yaml
most_queue/random/utils/base.py
most_queue/random/utils/create.py
most_queue/random/utils/fit.py
most_queue/random/utils/load.py
most_queue/random/utils/params.py
most_queue/sim/__init__.py
most_queue/sim/base.py
most_queue/sim/batch.py
most_queue/sim/finite_source.py
most_queue/sim/flow_sum.py
most_queue/sim/fork_join.py
most_queue/sim/fork_join_delta.py
most_queue/sim/impatient.py
most_queue/sim/negative.py
most_queue/sim/priority.py
most_queue/sim/vacations.py
most_queue/sim/networks/__init__.py
most_queue/sim/networks/base_network_sim.py
most_queue/sim/networks/network.py
most_queue/sim/networks/priority_network.py
most_queue/sim/utils/__init__.py
most_queue/sim/utils/phase.py
most_queue/sim/utils/qs_queue.py
most_queue/sim/utils/servers.py
most_queue/sim/utils/stats_update.py
most_queue/sim/utils/tasks.py
most_queue/theory/__init__.py
most_queue/theory/base_queue.py
most_queue/theory/calc_params.py
most_queue/theory/r_example.gexf
most_queue/theory/batch/__init__.py
most_queue/theory/batch/mm1.py
most_queue/theory/closed/__init__.py
most_queue/theory/closed/engset.py
most_queue/theory/fifo/__init__.py
most_queue/theory/fifo/ek_d_n.py
most_queue/theory/fifo/gi_m_1.py
most_queue/theory/fifo/gi_m_n.py
most_queue/theory/fifo/m_d_n.py
most_queue/theory/fifo/mg1.py
most_queue/theory/fifo/mgn_takahasi.py
most_queue/theory/fifo/mmnr.py
most_queue/theory/fork_join/__init__.py
most_queue-2.6.dist-info/METADATA
most_queue-2.6.dist-info/WHEEL
most_queue-2.6.dist-info/licenses/LICENSE
most_queue-2.6.dist-info/RECORD
