Metadata-Version: 2.4
Name: most_queue
Version: 2.6
Summary: Software package for calculation and simulation of queuing systems
Project-URL: Homepage, https://github.com/xabarov/most-queue
Author-email: Xabarov Roman <xabarov1985@gmail.com>
License: Copyright (c) 2018 The Python Packaging Authority
License-File: LICENSE
Classifier: License :: OSI Approved :: MIT License
Classifier: Operating System :: OS Independent
Classifier: Programming Language :: Python :: 3
Requires-Python: >=3.9
Requires-Dist: colorama
Requires-Dist: graphviz
Requires-Dist: matplotlib
Requires-Dist: networkx
Requires-Dist: numpy
Requires-Dist: pandas
Requires-Dist: pyyaml
Requires-Dist: scipy<2.0,>=1.13.0
Requires-Dist: tqdm
